{
    "title":"sort",
    "desc":"sort a matrix/map based on axis and given columns.",
    "input":[
	        {
                "name":"data", 
                "type":"map", 
                "description":"array of maps to be combines into one", 
                "optional":false
            }
	    ],
    "params":[
	        {
                "name":"ascending", 
                "type":"bool", 
                "description":"Sorting data in ascending", 
                "optional":false
            },
	        {
                "name":"axis", 
                "type":"int", 
                "description":"0=vertical/column, 1=horizontal/row.", 
            		"allowed" : [0, 1],
                "optional":false
            },
	        {
                "name":"nilPosition", 
                "type":"map", 
            		"description":"Puts Nils at the beginning if first; last puts Nils at the end.", 
            		"allowed" : ["first", "last"],
            		"optional":false
            },
        		{
            		"name":"by", 
            		"type":"array", 
            		"description":"sort by elements: 1. all are string -> conlumn label, 2. all are int (0 means first column) -> column number", 
            		"optional":false
        		}
	    ],
    "output":"map"
}
